tinybaker/__init__.py
tinybaker/cli.py
tinybaker/context.py
tinybaker/exceptions.py
tinybaker/fileref.py
tinybaker/namespace_transforms.py
tinybaker/parallel.py
tinybaker/scheduler.py
tinybaker/tag.py
tinybaker/transform.py
tinybaker/util.py
tinybaker/combinators/__init__.py
tinybaker/combinators/base.py
tinybaker/combinators/combinatormeta.py
tinybaker/combinators/map.py
tinybaker/combinators/merge.py
tinybaker/combinators/sequence.py
tinybaker/workarounds/__init__.py
tinybaker/workarounds/annot.py
tinybaker-0.4.0.dist-info/LICENSE
tinybaker-0.4.0.dist-info/METADATA
tinybaker-0.4.0.dist-info/WHEEL
tinybaker-0.4.0.dist-info/top_level.txt
tinybaker-0.4.0.dist-info/RECORD
