Metadata-Version: 2.1
Name: tinybaker
Version: 0.4.0
Summary: Lightweight file-to-file build tool built for production workloads
Home-page: https://github.com/pypa/tinybaker
Author: Evin Sellin
Author-email: evinism@gmail.com
License: UNKNOWN
Platform: UNKNOWN
Classifier: Programming Language :: Python :: 3
Classifier: License :: OSI Approved :: MIT License
Classifier: Operating System :: OS Independent
Requires-Python: >=3.6
Requires-Dist: fsspec
Requires-Dist: typeguard
Requires-Dist: contextvars ; python_version < "3.7"
